fba_bench_core/__init__.py
fba_bench_core/agents/__init__.py
fba_bench_core/agents/base.py
fba_bench_core/agents/registry.py
fba_bench_core/benchmarking/__init__.py
fba_bench_core/benchmarking/core/__init__.py
fba_bench_core/benchmarking/engine/__init__.py
fba_bench_core/benchmarking/engine/core.py
fba_bench_core/benchmarking/engine/models.py
fba_bench_core/benchmarking/metrics/__init__.py
fba_bench_core/benchmarking/metrics/accuracy_score.py
fba_bench_core/benchmarking/metrics/aggregate.py
fba_bench_core/benchmarking/metrics/completeness.py
fba_bench_core/benchmarking/metrics/cost_efficiency.py
fba_bench_core/benchmarking/metrics/custom_scriptable.py
fba_bench_core/benchmarking/metrics/keyword_coverage.py
fba_bench_core/benchmarking/metrics/policy_compliance.py
fba_bench_core/benchmarking/metrics/registry.py
fba_bench_core/benchmarking/metrics/robustness.py
fba_bench_core/benchmarking/metrics/technical_performance.py
fba_bench_core/benchmarking/registry.py
fba_bench_core/benchmarking/scenarios/__init__.py
fba_bench_core/benchmarking/scenarios/base.py
fba_bench_core/benchmarking/scenarios/complex_marketplace.py
fba_bench_core/benchmarking/scenarios/multiturn_tool_use.py
fba_bench_core/benchmarking/scenarios/registry.py
fba_bench_core/benchmarking/scenarios/research_summarization.py
fba_bench_core/benchmarking/validators/__init__.py
fba_bench_core/benchmarking/validators/determinism_check.py
fba_bench_core/benchmarking/validators/fairness_balance.py
fba_bench_core/benchmarking/validators/outlier_detection.py
fba_bench_core/benchmarking/validators/registry.py
fba_bench_core/benchmarking/validators/reproducibility_metadata.py
fba_bench_core/benchmarking/validators/schema_adherence.py
fba_bench_core/benchmarking/validators/structural_consistency.py
fba_bench_core/config.py
fba_bench_core/domain/__init__.py
fba_bench_core/domain/events/__init__.py
fba_bench_core/domain/events/analytics.py
fba_bench_core/domain/events/base.py
fba_bench_core/domain/events/inventory.py
fba_bench_core-1.0.0.dist-info/licenses/LICENSE
fba_bench_core-1.0.0.dist-info/METADATA
fba_bench_core-1.0.0.dist-info/WHEEL
fba_bench_core-1.0.0.dist-info/RECORD
