Metadata-Version: 2.4
Name: fba-bench-core
Version: 1.0.0
Summary: Core interfaces, data models, and events for the FBA-Bench simulation platform.
License: Apache-2.0
License-File: LICENSE
Keywords: benchmarking,simulation,fba,pydantic,typing
Author: FBA Team
Author-email: devnull@example.com
Requires-Python: >=3.11,<4.0
Classifier: Intended Audience :: Developers
Classifier: License :: OSI Approved :: Apache Software License
Classifier: Programming Language :: Python :: 3
Classifier: Programming Language :: Python :: 3.11
Classifier: Programming Language :: Python :: 3.12
Classifier: Programming Language :: Python :: 3.13
Classifier: Programming Language :: Python :: 3.14
Classifier: Topic :: Software Development :: Libraries
Classifier: Typing :: Typed
Requires-Dist: pydantic (>=2.0,<3.0)
Project-URL: Documentation, https://your-org.github.io/fba-bench-core
Project-URL: Homepage, https://github.com/your-org/fba-bench-core
Project-URL: Issues, https://github.com/your-org/fba-bench-core/issues
Project-URL: Repository, https://github.com/your-org/fba-bench-core
